pyclean/__init__.py
pyclean/__main__.py
pyclean/bytecode.py
pyclean/cli.py
pyclean/debris.py
pyclean/erase.py
pyclean/folders.py
pyclean/gitclean.py
pyclean/main.py
pyclean/runner.py
pyclean/traversal.py
pyclean-3.4.0.dist-info/licenses/LICENSES/GPL-3.0-or-later.txt
pyclean-3.4.0.dist-info/METADATA
pyclean-3.4.0.dist-info/WHEEL
pyclean-3.4.0.dist-info/entry_points.txt
pyclean-3.4.0.dist-info/top_level.txt
pyclean-3.4.0.dist-info/RECORD
