Metadata-Version: 2.4
Name: pyclean
Version: 3.4.0
Summary: Pure Python cross-platform pyclean. Clean up your Python bytecode.
Author-email: Peter Bittner <django@bittner.it>
Maintainer-email: Peter Bittner <django@bittner.it>
License-Expression: GPL-3.0-or-later
Project-URL: homepage, https://github.com/bittner/pyclean
Keywords: python,bytecode,cli,tools
Classifier: Development Status :: 5 - Production/Stable
Classifier: Intended Audience :: Developers
Classifier: Operating System :: OS Independent
Classifier: Programming Language :: Python
Classifier: Programming Language :: Python :: 3
Classifier: Programming Language :: Python :: 3 :: Only
Classifier: Programming Language :: Python :: 3.9
Classifier: Programming Language :: Python :: 3.10
Classifier: Programming Language :: Python :: 3.11
Classifier: Programming Language :: Python :: 3.12
Classifier: Programming Language :: Python :: 3.13
Classifier: Programming Language :: Python :: 3.14
Classifier: Programming Language :: Python :: Implementation :: CPython
Classifier: Programming Language :: Python :: Implementation :: PyPy
Classifier: Topic :: Utilities
Requires-Python: >=3.9
License-File: LICENSES/GPL-3.0-or-later.txt
Dynamic: license-file
